{
    "Tag": "Class",
    "Value": "nil",
    "Type_t": "Class",
    "Args": null,
    "ID": "",
    "Name": "",
    "Base": "class",
    "Methods": {
        "AddBreak": [
            {
                "Tag": "Function",
                "Value": "",
                "Type_t": "Function",
                "Args": null,
                "ID": "",
                "Name": "AddBreak",
                "Parameters": [],
                "Body": [
                    [
                        {
                            "Tag": "Return",
                            "Value": "nil",
                            "Type_t": "Return",
                            "Args": [
                                {
                                    "Tag": "Nary",
                                    "Value": "Add",
                                    "Type_t": "Operator",
                                    "Args": [
                                        {
                                            "Tag": "Identifier",
                                            "Value": "x",
                                            "Type_t": "Variable",
                                            "Args": null,
                                            "ID": "dccd25c9-1909-42f2-bea5-9f3b481398ce"
                                        },
                                        {
                                            "Tag": "Constant",
                                            "Value": "\"123\"",
                                            "Type_t": "String",
                                            "Args": null,
                                            "ID": "ede3cd2c-77e0-47d8-a4dd-f0a2bc6304a2"
                                        }
                                    ],
                                    "ID": "fe46c3e8-ac49-4a0d-ba33-f4d63d7d7330"
                                }
                            ],
                            "ID": "86d0585c-2f92-4b2c-a744-e40d5b18cb2d"
                        }
                    ]
                ]
            }
        ],
        "Get": [
            {
                "Tag": "Function",
                "Value": "",
                "Type_t": "Function",
                "Args": null,
                "ID": "",
                "Name": "Get",
                "Parameters": [],
                "Body": [
                    [
                        {
                            "Tag": "Return",
                            "Value": "nil",
                            "Type_t": "Return",
                            "Args": [
                                {
                                    "Tag": "Call",
                                    "Value": "nil",
                                    "Type_t": "Operator",
                                    "Args": [
                                        {
                                            "Tag": "Identifier",
                                            "Value": "Object",
                                            "Type_t": "Callable",
                                            "Args": null,
                                            "ID": "8a81a6f6-343b-44cb-bf5f-3ea44576161e"
                                        }
                                    ],
                                    "ID": ""
                                }
                            ],
                            "ID": "763e5fa1-506c-4935-9d1b-c5cf1380c175"
                        }
                    ]
                ]
            }
        ],
        "Hello": [
            {
                "Tag": "Function",
                "Value": "",
                "Type_t": "Function",
                "Args": null,
                "ID": "",
                "Name": "Hello",
                "Parameters": [
                    "x",
                    "y"
                ],
                "Body": [
                    [
                        {
                            "Tag": "Return",
                            "Value": "nil",
                            "Type_t": "Return",
                            "Args": [
                                {
                                    "Tag": "Nary",
                                    "Value": "Add",
                                    "Type_t": "Operator",
                                    "Args": [
                                        {
                                            "Tag": "Identifier",
                                            "Value": "x",
                                            "Type_t": "Variable",
                                            "Args": null,
                                            "ID": "a5aa7c6f-92d4-4ca7-8b78-38808ede4c44"
                                        },
                                        {
                                            "Tag": "Identifier",
                                            "Value": "y",
                                            "Type_t": "Variable",
                                            "Args": null,
                                            "ID": "11e748aa-6ccf-4cec-bda5-ed15206497aa"
                                        }
                                    ],
                                    "ID": "9edaf420-099b-4bf6-91d7-8b55fee630e2"
                                }
                            ],
                            "ID": "995bb615-32a0-48f3-b748-0cc3305b83a6"
                        }
                    ]
                ]
            }
        ],
        "SetMsg": [
            {
                "Tag": "Function",
                "Value": "",
                "Type_t": "Function",
                "Args": null,
                "ID": "",
                "Name": "SetMsg",
                "Parameters": [
                    "msg"
                ],
                "Body": [
                    [
                        {
                            "Tag": "Binary",
                            "Value": "Eq",
                            "Type_t": "Operator",
                            "Args": [
                                {
                                    "Tag": "Member",
                                    "Value": "msg",
                                    "Type_t": "Member",
                                    "Args": null,
                                    "ID": "4b86bb0b-858c-465e-a5aa-5a0a8e446f84"
                                },
                                {
                                    "Tag": "Identifier",
                                    "Value": "msg",
                                    "Type_t": "Variable",
                                    "Args": null,
                                    "ID": "f31c9a08-89d9-4a81-8526-51cce4661a1c"
                                }
                            ],
                            "ID": "75305337-526d-4e3f-9062-aeaa3a6e2ab4"
                        }
                    ]
                ]
            }
        ],
        "SetX": [
            {
                "Tag": "Function",
                "Value": "",
                "Type_t": "Function",
                "Args": null,
                "ID": "",
                "Name": "SetX",
                "Parameters": [
                    "x"
                ],
                "Body": [
                    [
                        {
                            "Tag": "Binary",
                            "Value": "Eq",
                            "Type_t": "Operator",
                            "Args": [
                                {
                                    "Tag": "Member",
                                    "Value": "x",
                                    "Type_t": "Member",
                                    "Args": null,
                                    "ID": "a7da5abf-be98-45a9-ac1e-447a157148f2"
                                },
                                {
                                    "Tag": "Identifier",
                                    "Value": "x",
                                    "Type_t": "Variable",
                                    "Args": null,
                                    "ID": "a08c382f-a603-47b1-821b-10df8ae8b43a"
                                }
                            ],
                            "ID": "1bf5dd6b-4aa1-427c-9b13-86193c12a248"
                        }
                    ]
                ]
            }
        ],
        "originalTestFunc": [
            {
                "Tag": "Function",
                "Value": "",
                "Type_t": "Function",
                "Args": null,
                "ID": "",
                "Name": "originalTestFunc",
                "Parameters": [
                    "x",
                    "y",
                    "z"
                ],
                "Body": [
                    [
                        {
                            "Tag": "Binary",
                            "Value": "Eq",
                            "Type_t": "Operator",
                            "Args": [
                                {
                                    "Tag": "Identifier",
                                    "Value": "num",
                                    "Type_t": "Variable",
                                    "Args": null,
                                    "ID": "6dbe71ff-1df1-4697-987d-6ab8892f6b92"
                                },
                                {
                                    "Tag": "Nary",
                                    "Value": "Add",
                                    "Type_t": "Operator",
                                    "Args": [
                                        {
                                            "Tag": "Identifier",
                                            "Value": "x",
                                            "Type_t": "Variable",
                                            "Args": null,
                                            "ID": "eeed4993-02dd-48b0-8a37-74f4ee2a6c85"
                                        },
                                        {
                                            "Tag": "Constant",
                                            "Value": "123",
                                            "Type_t": "Number",
                                            "Args": null,
                                            "ID": "1a6c8c59-9aac-41f4-b300-45db60b87ed3"
                                        }
                                    ],
                                    "ID": "422e6379-338b-4e61-833c-90520a0fd16e"
                                }
                            ],
                            "ID": "c4b0ba6d-92dd-471d-92ac-6dfe8ec7f5e4"
                        }
                    ],
                    [
                        {
                            "Tag": "Unary",
                            "Value": "PostInc",
                            "Type_t": "PostInc",
                            "Args": [
                                {
                                    "Tag": "Identifier",
                                    "Value": "num",
                                    "Type_t": "Variable",
                                    "Args": null,
                                    "ID": "629359d6-7621-44e5-86ed-4a9663d93c06"
                                }
                            ],
                            "ID": "17ff60ab-7bce-49b1-8290-e4657fc98521"
                        }
                    ],
                    [
                        {
                            "Tag": "If",
                            "Value": "nil",
                            "Type_t": "If",
                            "Args": [
                                {
                                    "Tag": "Nary",
                                    "Value": "And",
                                    "Type_t": "Operator",
                                    "Args": [
                                        {
                                            "Tag": "Call",
                                            "Value": "nil",
                                            "Type_t": "Operator",
                                            "Args": [
                                                {
                                                    "Tag": "Identifier",
                                                    "Value": "String?",
                                                    "Type_t": "Callable",
                                                    "Args": null,
                                                    "ID": "621b9d72-8d75-4ce4-b826-5121a89cf38a"
                                                }
                                            ],
                                            "ID": ""
                                        },
                                        {
                                            "Tag": "Call",
                                            "Value": "nil",
                                            "Type_t": "Operator",
                                            "Args": [
                                                {
                                                    "Tag": "Identifier",
                                                    "Value": "Number?",
                                                    "Type_t": "Callable",
                                                    "Args": null,
                                                    "ID": "cbec9a79-0277-4365-8986-78bea901dd42"
                                                }
                                            ],
                                            "ID": ""
                                        }
                                    ],
                                    "ID": "c94d291d-32ab-4dc4-9317-39bb7d03ace5"
                                },
                                {
                                    "Tag": "Compound",
                                    "Value": "nil",
                                    "Type_t": "Compound",
                                    "Args": [
                                        {
                                            "Tag": "Binary",
                                            "Value": "Eq",
                                            "Type_t": "Operator",
                                            "Args": [
                                                {
                                                    "Tag": "Identifier",
                                                    "Value": "abc",
                                                    "Type_t": "Variable",
                                                    "Args": null,
                                                    "ID": "522568ad-d145-432d-a89e-13df8e131789"
                                                },
                                                {
                                                    "Tag": "Nary",
                                                    "Value": "Add",
                                                    "Type_t": "Operator",
                                                    "Args": [
                                                        {
                                                            "Tag": "Identifier",
                                                            "Value": "x",
                                                            "Type_t": "Variable",
                                                            "Args": null,
                                                            "ID": "9004f736-2738-4a21-a45e-b48fbe59a49a"
                                                        },
                                                        {
                                                            "Tag": "Identifier",
                                                            "Value": "y",
                                                            "Type_t": "Variable",
                                                            "Args": null,
                                                            "ID": "621104db-8b29-4fbc-bf14-eef41c4f4dae"
                                                        },
                                                        {
                                                            "Tag": "Identifier",
                                                            "Value": "z",
                                                            "Type_t": "Variable",
                                                            "Args": null,
                                                            "ID": "81c5ba30-7920-4a45-ba4d-3f815e42afdc"
                                                        },
                                                        {
                                                            "Tag": "Identifier",
                                                            "Value": "num",
                                                            "Type_t": "Variable",
                                                            "Args": null,
                                                            "ID": "a3ae4c80-b25b-4316-afec-9067a084d6eb"
                                                        }
                                                    ],
                                                    "ID": "0d5d880c-7dc8-42fe-ac14-4a27c6d6ad5d"
                                                }
                                            ],
                                            "ID": "64603f80-bd84-4e67-a7df-1f227e2ea323"
                                        }
                                    ],
                                    "ID": "21a1a1f5-7a5a-4bd8-8453-01c40befe1e4"
                                },
                                {
                                    "Tag": "Compound",
                                    "Value": "nil",
                                    "Type_t": "Compound",
                                    "Args": [
                                        {
                                            "Tag": "Call",
                                            "Value": "nil",
                                            "Type_t": "Operator",
                                            "Args": [
                                                {
                                                    "Tag": "Identifier",
                                                    "Value": "num",
                                                    "Type_t": "Callable",
                                                    "Args": null,
                                                    "ID": "4bb7ddc1-bd91-489c-9221-d1c95238e07f"
                                                }
                                            ],
                                            "ID": ""
                                        }
                                    ],
                                    "ID": "77b4a113-897c-4c23-89d2-d68b96775d04"
                                }
                            ],
                            "ID": "cfaeefd0-d087-4ea4-be69-6d24699f4ba7"
                        }
                    ],
                    [
                        {
                            "Tag": "Call",
                            "Value": "nil",
                            "Type_t": "Operator",
                            "Args": [
                                {
                                    "Tag": "Identifier",
                                    "Value": "this.qux",
                                    "Type_t": "Callable",
                                    "Args": null,
                                    "ID": "24f4c6f6-1ecd-4ed7-a3bc-d573dbcd64a4"
                                }
                            ],
                            "ID": ""
                        }
                    ]
                ]
            }
        ],
        "pvt_bar": [
            {
                "Tag": "Function",
                "Value": "",
                "Type_t": "Function",
                "Args": null,
                "ID": "",
                "Name": "pvt_bar",
                "Parameters": [],
                "Body": [
                    [
                        {
                            "Tag": "Return",
                            "Value": "nil",
                            "Type_t": "Return",
                            "Args": [
                                {
                                    "Tag": "Member",
                                    "Value": "msg",
                                    "Type_t": "Member",
                                    "Args": null,
                                    "ID": "4a717826-ccc9-4155-9f9f-432ff7178264"
                                }
                            ],
                            "ID": "5d3970d6-a233-477f-9d78-6393d3e4f051"
                        }
                    ]
                ]
            }
        ],
        "pvt_foo": [
            {
                "Tag": "Function",
                "Value": "",
                "Type_t": "Function",
                "Args": null,
                "ID": "",
                "Name": "pvt_foo",
                "Parameters": [],
                "Body": [
                    [
                        {
                            "Tag": "Return",
                            "Value": "nil",
                            "Type_t": "Return",
                            "Args": [
                                {
                                    "Tag": "Member",
                                    "Value": "x",
                                    "Type_t": "Member",
                                    "Args": null,
                                    "ID": "27462046-5bf7-4921-892d-377c7d1d8695"
                                }
                            ],
                            "ID": "e0abc59c-7f97-453c-b594-28d49bb385fc"
                        }
                    ]
                ]
            }
        ]
    },
    "Attributes": {
        "msg": [
            {
                "Tag": "Constant",
                "Value": "hello",
                "Type_t": "String",
                "Args": null,
                "ID": "a46f358e-4d43-4065-8790-9848017b8906"
            }
        ],
        "x": [
            {
                "Tag": "Constant",
                "Value": "0",
                "Type_t": "Number",
                "Args": null,
                "ID": "4de318ae-067a-40ff-bc6a-e953d7b98749"
            }
        ]
    }
}