{
    "nodes": [
        {
            "value": "String",
            "sutype": "String",
            "edges": [
                "1859e18eb61248bd9597ec8ad0ff99a5",
                "1181882966884ef4a83cc5e22025d6b7",
                "92af96595c7243b3af61c37922c174be",
                "3b3dd2f2b27e4fa481a4e9079ed1249e",
                "6d94b3a703af4d32b30d40db5db9d2bc"
            ]
        },
        {
            "value": "Number",
            "sutype": "Number",
            "edges": [
                "33a7a03698ed4e499257b06de6b68555",
                "d2807671c5ed477d98927275883f6226",
                "ed54ae11a5914f73833874d61f1cc957",
                "9c43a1d760664a2c9e46e69bd5d0abdf",
                "9f1fba649e0549c28b03c7e70f45e4f9",
                "ba40e1f308d24133b67f93e8de084ee0",
                "de3ed5df2c1647fba8f2f3e50bb05832",
                "98d3ed99aa9d4a73b9c82aac4dff997d",
                "2f7c82f9cb11433bbb2a5a880631c48e",
                "f3db41f6607843ae81b5e865332ef7b4",
                "6526a4f8426749748dfff84c89eb987b",
                "fd8839d097c3454a924e864451d3f558",
                "a0f404487f4e4d218db6d2415dc8c121",
                "f106d4cc938f450f92b5eeaf6cad2644",
                "1fab48e8b94d4aeaaecf9ef76ade85d3",
                "503651d990d341808313d5fb90d8a94d"
            ]
        },
        {
            "value": "Boolean",
            "sutype": "Boolean",
            "edges": [
                "c3c986a2252d432a91a043ccdc43410b"
            ]
        },
        {
            "value": "Any",
            "sutype": "Any",
            "edges": [
                "d084d19f5d6a45948670307d1b3c124f",
                "3b8a829d49aa403b984a92c3b50aeac9"
            ]
        },
        {
            "value": "NotApplicable",
            "sutype": "NotApplicable",
            "edges": []
        },
        {
            "value": "Never",
            "sutype": "Never",
            "edges": []
        },
        {
            "value": "Function",
            "sutype": "Function",
            "edges": []
        },
        {
            "value": "Object",
            "sutype": "Object",
            "edges": [
                "7eca40a25c5a44d4b90da53412ca570a"
            ]
        },
        {
            "value": "InBuiltOperator",
            "sutype": "InBuiltOperator",
            "edges": []
        },
        {
            "value": "57fd14cedc2f4104a4b03c0bc7a35c4a",
            "sutype": "Number",
            "edges": [
                "33a7a03698ed4e499257b06de6b68555"
            ]
        },
        {
            "value": "33a7a03698ed4e499257b06de6b68555",
            "sutype": "Number",
            "edges": [
                "57fd14cedc2f4104a4b03c0bc7a35c4a",
                "Number"
            ]
        },
        {
            "value": "d2807671c5ed477d98927275883f6226",
            "sutype": "Number",
            "edges": [
                "Number"
            ]
        },
        {
            "value": "ed54ae11a5914f73833874d61f1cc957",
            "sutype": "Number",
            "edges": [
                "Number"
            ]
        },
        {
            "value": "1859e18eb61248bd9597ec8ad0ff99a5",
            "sutype": "String",
            "edges": [
                "String"
            ]
        },
        {
            "value": "9c43a1d760664a2c9e46e69bd5d0abdf",
            "sutype": "Number",
            "edges": [
                "Number"
            ]
        },
        {
            "value": "9f1fba649e0549c28b03c7e70f45e4f9",
            "sutype": "Number",
            "edges": [
                "Number"
            ]
        },
        {
            "value": "d084d19f5d6a45948670307d1b3c124f",
            "sutype": "Any",
            "edges": [
                "Any"
            ]
        },
        {
            "value": "7eca40a25c5a44d4b90da53412ca570a",
            "sutype": "Object",
            "edges": [
                "Object"
            ]
        },
        {
            "value": "d7fcaee406ed4061876199ad9e698e99",
            "sutype": "Number",
            "edges": [
                "ba40e1f308d24133b67f93e8de084ee0"
            ]
        },
        {
            "value": "ba40e1f308d24133b67f93e8de084ee0",
            "sutype": "Number",
            "edges": [
                "d7fcaee406ed4061876199ad9e698e99",
                "Number"
            ]
        },
        {
            "value": "de3ed5df2c1647fba8f2f3e50bb05832",
            "sutype": "Number",
            "edges": [
                "Number"
            ]
        },
        {
            "value": "1181882966884ef4a83cc5e22025d6b7",
            "sutype": "String",
            "edges": [
                "String",
                "e11cc9b390fd4c0c9f48f4dfa24eb4db"
            ]
        },
        {
            "value": "e11cc9b390fd4c0c9f48f4dfa24eb4db",
            "sutype": "String",
            "edges": [
                "1181882966884ef4a83cc5e22025d6b7"
            ]
        },
        {
            "value": "92af96595c7243b3af61c37922c174be",
            "sutype": "String",
            "edges": [
                "String"
            ]
        },
        {
            "value": "98d3ed99aa9d4a73b9c82aac4dff997d",
            "sutype": "Number",
            "edges": [
                "Number",
                "5d67f39136684bf686d27871110c2cc3"
            ]
        },
        {
            "value": "5d67f39136684bf686d27871110c2cc3",
            "sutype": "Number",
            "edges": [
                "98d3ed99aa9d4a73b9c82aac4dff997d"
            ]
        },
        {
            "value": "2f7c82f9cb11433bbb2a5a880631c48e",
            "sutype": "Number",
            "edges": [
                "Number"
            ]
        },
        {
            "value": "757e479a03af4e0f9852aa84e84fc7dc",
            "sutype": "Number",
            "edges": [
                "f3db41f6607843ae81b5e865332ef7b4"
            ]
        },
        {
            "value": "f3db41f6607843ae81b5e865332ef7b4",
            "sutype": "Number",
            "edges": [
                "757e479a03af4e0f9852aa84e84fc7dc",
                "Number"
            ]
        },
        {
            "value": "3912bd905bf44bb7b8acf306af0b228e",
            "sutype": "Unknown",
            "edges": [
                "ac1796c6ade3451eb0bf51a668c72f46"
            ]
        },
        {
            "value": "ac1796c6ade3451eb0bf51a668c72f46",
            "sutype": "Unknown",
            "edges": [
                "3912bd905bf44bb7b8acf306af0b228e"
            ]
        },
        {
            "value": "6526a4f8426749748dfff84c89eb987b",
            "sutype": "Number",
            "edges": [
                "Number"
            ]
        },
        {
            "value": "fd8839d097c3454a924e864451d3f558",
            "sutype": "Number",
            "edges": [
                "Number"
            ]
        },
        {
            "value": "a0f404487f4e4d218db6d2415dc8c121",
            "sutype": "Number",
            "edges": [
                "Number"
            ]
        },
        {
            "value": "49b03b63d38e48eaaa39cdcb0921e7f9",
            "sutype": "Boolean",
            "edges": [
                "c3c986a2252d432a91a043ccdc43410b"
            ]
        },
        {
            "value": "c3c986a2252d432a91a043ccdc43410b",
            "sutype": "Boolean",
            "edges": [
                "49b03b63d38e48eaaa39cdcb0921e7f9",
                "Boolean"
            ]
        },
        {
            "value": "e717e01ff2a34ce49b2ac7071d670f9a",
            "sutype": "Number",
            "edges": [
                "e38b218b4c7a4f758ff9aa429ff4194d"
            ]
        },
        {
            "value": "e38b218b4c7a4f758ff9aa429ff4194d",
            "sutype": "Number",
            "edges": [
                "e717e01ff2a34ce49b2ac7071d670f9a",
                "fe66162d53a7461691d2c44e9af52c97"
            ]
        },
        {
            "value": "fe66162d53a7461691d2c44e9af52c97",
            "sutype": "Number",
            "edges": [
                "e38b218b4c7a4f758ff9aa429ff4194d",
                "f106d4cc938f450f92b5eeaf6cad2644"
            ]
        },
        {
            "value": "f106d4cc938f450f92b5eeaf6cad2644",
            "sutype": "Number",
            "edges": [
                "fe66162d53a7461691d2c44e9af52c97",
                "Number"
            ]
        },
        {
            "value": "b504f797a7634c59a2880ba38e31e648",
            "sutype": "Unknown",
            "edges": [
                "bc8bbe411b8d4f4bb6e780418196c56c"
            ]
        },
        {
            "value": "bc8bbe411b8d4f4bb6e780418196c56c",
            "sutype": "Unknown",
            "edges": [
                "b504f797a7634c59a2880ba38e31e648"
            ]
        },
        {
            "value": "3b8a829d49aa403b984a92c3b50aeac9",
            "sutype": "Any",
            "edges": [
                "Any"
            ]
        },
        {
            "value": "3b3dd2f2b27e4fa481a4e9079ed1249e",
            "sutype": "String",
            "edges": [
                "String"
            ]
        },
        {
            "value": "6d94b3a703af4d32b30d40db5db9d2bc",
            "sutype": "String",
            "edges": [
                "String"
            ]
        },
        {
            "value": "1fab48e8b94d4aeaaecf9ef76ade85d3",
            "sutype": "Number",
            "edges": [
                "Number"
            ]
        },
        {
            "value": "503651d990d341808313d5fb90d8a94d",
            "sutype": "Number",
            "edges": [
                "Number"
            ]
        }
    ]
}